omniscale/__init__.py
omniscale/cli.py
omniscale/currency_converter.py
omniscale/module.py
omniscale/update_rates.py
omniscale-0.2.dist-info/METADATA
omniscale-0.2.dist-info/WHEEL
omniscale-0.2.dist-info/top_level.txt
omniscale-0.2.dist-info/RECORD
