Metadata-Version: 2.1
Name: omniscale
Version: 0.2
Summary: A Python package for various unit conversions
Home-page: https://github.com/AleksandarOvcharov/Omniscale
Author: Valhal4o1331
Classifier: Programming Language :: Python :: 3
Classifier: License :: OSI Approved :: MIT License
Classifier: Operating System :: OS Independent
Requires-Python: >=3.6
